beetsplug/__init__.py
beetsplug/ytimport/__init__.py
beetsplug/ytimport/config_default.yaml
beetsplug/ytimport/safename.py
beetsplug/ytimport/split.py
beetsplug/ytimport/youtube.py
beets_ytimport-1.12.1.dist-info/LICENSE
beets_ytimport-1.12.1.dist-info/METADATA
beets_ytimport-1.12.1.dist-info/WHEEL
beets_ytimport-1.12.1.dist-info/top_level.txt
beets_ytimport-1.12.1.dist-info/RECORD
