Metadata-Version: 2.1
Name: beets-ytimport
Version: 1.12.1
Summary: Download audio from Youtube into your Beets library
Home-page: https://github.com/mgoltzsche/beets-ytimport
Author: Max Goltzsche
License: UNKNOWN
Platform: UNKNOWN
Classifier: Programming Language :: Python :: 3.6
Classifier: License :: OSI Approved :: Apache Software License
Classifier: Operating System :: OS Independent
License-File: LICENSE
Requires-Dist: beets
Requires-Dist: ytmusicapi
Requires-Dist: yt-dlp
